odoo10_addon_sale_isolated_quotation-10.0.1.0.1-py3.8-nspkg.pth
odoo/addons/sale_isolated_quotation/README.rst
odoo/addons/sale_isolated_quotation/__init__.py
odoo/addons/sale_isolated_quotation/__manifest__.py
odoo/addons/sale_isolated_quotation/hooks.py
odoo/addons/sale_isolated_quotation/data/ir_sequence_data.xml
odoo/addons/sale_isolated_quotation/i18n/ca.po
odoo/addons/sale_isolated_quotation/i18n/de.po
odoo/addons/sale_isolated_quotation/i18n/el_GR.po
odoo/addons/sale_isolated_quotation/i18n/es.po
odoo/addons/sale_isolated_quotation/i18n/es_ES.po
odoo/addons/sale_isolated_quotation/i18n/es_VE.po
odoo/addons/sale_isolated_quotation/i18n/fi.po
odoo/addons/sale_isolated_quotation/i18n/fr.po
odoo/addons/sale_isolated_quotation/i18n/hr.po
odoo/addons/sale_isolated_quotation/i18n/hr_HR.po
odoo/addons/sale_isolated_quotation/i18n/hu.po
odoo/addons/sale_isolated_quotation/i18n/it.po
odoo/addons/sale_isolated_quotation/i18n/nl.po
odoo/addons/sale_isolated_quotation/i18n/nl_NL.po
odoo/addons/sale_isolated_quotation/i18n/pt.po
odoo/addons/sale_isolated_quotation/i18n/pt_BR.po
odoo/addons/sale_isolated_quotation/i18n/ro.po
odoo/addons/sale_isolated_quotation/i18n/sale_isolated_quotation.pot
odoo/addons/sale_isolated_quotation/i18n/sk.po
odoo/addons/sale_isolated_quotation/i18n/sl.po
odoo/addons/sale_isolated_quotation/i18n/tr.po
odoo/addons/sale_isolated_quotation/i18n/tr_TR.po
odoo/addons/sale_isolated_quotation/i18n/vi_VN.po
odoo/addons/sale_isolated_quotation/i18n/zh_CN.po
odoo/addons/sale_isolated_quotation/models/__init__.py
odoo/addons/sale_isolated_quotation/models/sale.py
odoo/addons/sale_isolated_quotation/static/description/icon.png
odoo/addons/sale_isolated_quotation/tests/__init__.py
odoo/addons/sale_isolated_quotation/tests/test_sale_isolated_quotation.py
odoo/addons/sale_isolated_quotation/views/sale_views.xml
odoo10_addon_sale_isolated_quotation-10.0.1.0.1.dist-info/METADATA
odoo10_addon_sale_isolated_quotation-10.0.1.0.1.dist-info/WHEEL
odoo10_addon_sale_isolated_quotation-10.0.1.0.1.dist-info/namespace_packages.txt
odoo10_addon_sale_isolated_quotation-10.0.1.0.1.dist-info/top_level.txt
odoo10_addon_sale_isolated_quotation-10.0.1.0.1.dist-info/RECORD
