Metadata-Version: 2.1
Name: odoo10-addon-sale-isolated-quotation
Version: 10.0.1.0.1
Summary: Sales - Isolated Quotation
Home-page: https://github.com/OCA/sale-workflow
Author: Ecosoft,Odoo Community Association (OCA)
Author-email: support@odoo-community.org
License: AGPL-3
Platform: UNKNOWN
Classifier: Programming Language :: Python
Classifier: Framework :: Odoo
Classifier: Framework :: Odoo :: 10.0
Classifier: License :: OSI Approved :: GNU Affero General Public License v3
Requires-Python: ~=2.7
Requires-Dist: odoo (<10.1dev,>=10.0)
